mbf_genomes/__init__.py
mbf_genomes/base.py
mbf_genomes/common.py
mbf_genomes/ensembl.py
mbf_genomes/filebased.py
mbf_genomes/gene.py
mbf_genomes/data/info.txt
mbf_genomes/data/polish_ribosomal.py
mbf_genomes/data/ribosomal_genes_grch37.gtf.gz
mbf_genomes/data/ribosomal_genes_grch37.gtf.gz.full.gtf.gz
mbf_genomes/data/ribosomal_genes_grch38.gtf.gz
mbf_genomes/data/ribosomal_genes_grch38.gtf.gz.full.gtf.gz
mbf_genomes/data/ribosomal_genes_mm10.gtf.gz
mbf_genomes/data/ribosomal_genes_mm10.gtf.gz.full.gtf.gz
mbf_genomes/data/ustilago_maydis_a2_locus.fasta
mbf_genomes/data/ustilago_maydis_a2_locus.gff
mbf_genomes/data/liftovers/hg19ToHg38.over.chain
mbf_genomes/data/liftovers/info.txt
mbf_genomes/data/liftovers/mm8ToMm10.over.chain
mbf_genomes/data/liftovers/mm8ToMm9.over.chain
mbf_genomes/data/liftovers/mm9ToMm10.over.chain
mbf_genomes/testing/__init__.py
mbf_genomes/testing/fixtures.py
mbf_genomes-0.4.dist-info/AUTHORS.rst
mbf_genomes-0.4.dist-info/LICENSE.txt
mbf_genomes-0.4.dist-info/METADATA
mbf_genomes-0.4.dist-info/WHEEL
mbf_genomes-0.4.dist-info/top_level.txt
mbf_genomes-0.4.dist-info/RECORD
